cezzis_otel/__init__.py
cezzis_otel/__init__.pyi
cezzis_otel/otel.py
cezzis_otel/otel.pyi
cezzis_otel/otel_settings.py
cezzis_otel/otel_settings.pyi
cezzis_otel-0.0.25.dist-info/METADATA
cezzis_otel-0.0.25.dist-info/WHEEL
cezzis_otel-0.0.25.dist-info/RECORD
