Metadata-Version: 2.4
Name: cezzis_otel
Version: 0.0.25
Summary: cezzis-otel is a lightweight Python library for working with opentelemetry.  It simplifies otel collector and otlpexporter integration.
License: MIT
Author: mtnvencenzo
Author-email: rvecchi@gmail.com
Requires-Python: >=3.12,<3.15
Classifier: License :: OSI Approved :: MIT License
Classifier: Programming Language :: Python :: 3
Classifier: Programming Language :: Python :: 3.12
Classifier: Programming Language :: Python :: 3.13
Classifier: Programming Language :: Python :: 3.14
Requires-Dist: opentelemetry-api (>=1.38.0,<2.0.0)
Requires-Dist: opentelemetry-exporter-otlp (>=1.38.0,<2.0.0)
Requires-Dist: opentelemetry-instrumentation-logging (>=0.59b0,<0.60)
Requires-Dist: opentelemetry-instrumentation-requests (>=0.59b0,<0.60)
Requires-Dist: opentelemetry-sdk (>=1.38.0,<2.0.0)
Requires-Dist: opentelemetry-semantic-conventions (>=0.59b0,<0.60)
